{
    "Escape": {
        "name": "Esc",
        "width": 1,
        "column": 0,
        "row": 0
    },
    "Digit1": {
        "name": "1 !",
        "width": 1,
        "column": 1,
        "row": 0
    },
    "Digit2": {
        "name": "2 @",
        "width": 1,
        "column": 2,
        "row": 0
    },
    "Digit3": {
        "name": "3 #",
        "width": 1,
        "column": 3,
        "row": 0
    },
    "Digit4": {
        "name": "4 $",
        "width": 1,
        "column": 4,
        "row": 0
    },
    "Digit5": {
        "name": "5 %",
        "width": 1,
        "column": 5,
        "row": 0
    },
    "Digit6": {
        "name": "6 ^",
        "width": 1,
        "column": 6,
        "row": 0
    },
    "Digit7": {
        "name": "7 &",
        "width": 1,
        "column": 7,
        "row": 0
    },
    "Digit8": {
        "name": "8 *",
        "width": 1,
        "column": 8,
        "row": 0
    },
    "Digit9": {
        "name": "9 (",
        "width": 1,
        "column": 9,
        "row": 0
    },
    "Digit0": {
        "name": "0 )",
        "width": 1,
        "column": 10,
        "row": 0
    },
    "Minus": {
        "name": "- _",
        "width": 1,
        "column": 11,
        "row": 0
    },
    "Equal": {
        "name": "= +",
        "width": 1,
        "column": 12,
        "row": 0
    },
    "Backspace": {
        "name": "⟵",
        "width": 2,
        "column": 13,
        "row": 0
    },
    "Home": {
        "name": "Home",
        "width": 1,
        "column": 15,
        "row": 0
    },
    "Tab": {
        "name": "Tab",
        "width": 1.5,
        "column": 0,
        "row": 1
    },
    "KeyQ": {
        "name": "Q",
        "width": 1,
        "column": 1.5,
        "row": 1
    },
    "KeyW": {
        "name": "W",
        "width": 1,
        "column": 2.5,
        "row": 1
    },
    "KeyE": {
        "name": "E",
        "width": 1,
        "column": 3.5,
        "row": 1
    },
    "KeyR": {
        "name": "R",
        "width": 1,
        "column": 4.5,
        "row": 1
    },
    "KeyT": {
        "name": "T",
        "width": 1,
        "column": 5.5,
        "row": 1
    },
    "KeyY": {
        "name": "Y",
        "width": 1,
        "column": 6.5,
        "row": 1
    },
    "KeyU": {
        "name": "U",
        "width": 1,
        "column": 7.5,
        "row": 1
    },
    "KeyI": {
        "name": "I",
        "width": 1,
        "column": 8.5,
        "row": 1
    },
    "KeyO": {
        "name": "O",
        "width": 1,
        "column": 9.5,
        "row": 1
    },
    "KeyP": {
        "name": "P",
        "width": 1,
        "column": 10.5,
        "row": 1
    },
    "BracketLeft": {
        "name": "[",
        "width": 1,
        "column": 11.5,
        "row": 1
    },
    "BracketRight": {
        "name": "]",
        "width": 1,
        "column": 12.5,
        "row": 1
    },
    "Backslash": {
        "name": "\\",
        "width": 1.5,
        "column": 13.5,
        "row": 1
    },
    "Delete": {
        "name": "Del",
        "width": 1,
        "column": 15,
        "row": 1
    },
    "CapsLock": {
        "name": "Caps",
        "width": 1.75,
        "column": 0,
        "row": 2
    },
    "KeyA": {
        "name": "A",
        "width": 1,
        "column": 1.75,
        "row": 2
    },
    "KeyS": {
        "name": "S",
        "width": 1,
        "column": 2.75,
        "row": 2
    },
    "KeyD": {
        "name": "D",
        "width": 1,
        "column": 3.75,
        "row": 2
    },
    "KeyF": {
        "name": "F",
        "width": 1,
        "column": 4.75,
        "row": 2
    },
    "KeyG": {
        "name": "G",
        "width": 1,
        "column": 5.75,
        "row": 2
    },
    "KeyH": {
        "name": "H",
        "width": 1,
        "column": 6.75,
        "row": 2
    },
    "KeyJ": {
        "name": "J",
        "width": 1,
        "column": 7.75,
        "row": 2
    },
    "KeyK": {
        "name": "K",
        "width": 1,
        "column": 8.75,
        "row": 2
    },
    "KeyL": {
        "name": "L",
        "width": 1,
        "column": 9.75,
        "row": 2
    },
    "Semicolon": {
        "name": ";",
        "width": 1,
        "column": 10.75,
        "row": 2
    },
    "Quote": {
        "name": "'",
        "width": 1,
        "column": 11.75,
        "row": 2
    },
    "Enter": {
        "name": "Enter",
        "width": 2.25,
        "column": 12.75,
        "row": 2
    },
    "PageUp": {
        "name": "PgUp",
        "width": 1,
        "column": 15,
        "row": 2
    },
    "ShiftLeft": {
        "name": "Shift",
        "width": 2.25,
        "column": 0,
        "row": 3
    },
    "KeyZ": {
        "name": "Z",
        "width": 1,
        "column": 2.25,
        "row": 3
    },
    "KeyX": {
        "name": "X",
        "width": 1,
        "column": 3.25,
        "row": 3
    },
    "KeyC": {
        "name": "C",
        "width": 1,
        "column": 4.25,
        "row": 3
    },
    "KeyV": {
        "name": "V",
        "width": 1,
        "column": 5.25,
        "row": 3
    },
    "KeyB": {
        "name": "B",
        "width": 1,
        "column": 6.25,
        "row": 3
    },
    "KeyN": {
        "name": "N",
        "width": 1,
        "column": 7.25,
        "row": 3
    },
    "KeyM": {
        "name": "M",
        "width": 1,
        "column": 8.25,
        "row": 3
    },
    "Comma": {
        "name": ", <",
        "width": 1,
        "column": 9.25,
        "row": 3
    },
    "Period": {
        "name": ". >",
        "width": 1,
        "column": 10.25,
        "row": 3
    },
    "Slash": {
        "name": "/ ?",
        "width": 1,
        "column": 11.25,
        "row": 3
    },
    "ShiftRight": {
        "name": "Shift",
        "width": 1.75,
        "column": 12.25,
        "row": 3
    },
    "ArrowUp": {
        "name": "↑",
        "width": 1,
        "column": 14,
        "row": 3
    },
    "PageDown": {
        "name": "PgDn",
        "width": 1,
        "column": 15,
        "row": 3
    },
    "ContrlLeft": {
        "name": "Ctrl",
        "width": 1.25,
        "column": 0,
        "row": 4
    },
    "MetaLeft": {
        "name": "Win",
        "width": 1.25,
        "column": 1.25,
        "row": 4
    },
    "AltLeft": {
        "name": "Alt",
        "width": 1.25,
        "column": 2.5,
        "row": 4
    },
    "Space": {
        "name": "⎯⎯⎯⎯⎯⎯",
        "width": 6.25,
        "column": 3.75,
        "row": 4
    },
    "AltRight": {
        "name": "Alt",
        "width": 1,
        "column": 10,
        "row": 4
    },
    "#Fn": {
        "name": "Fn",
        "width": 1,
        "column": 11,
        "row": 4
    },
    "ControlRight": {
        "name": "Ctrl",
        "width": 1,
        "column": 12,
        "row": 4
    },
    "ArrowLeft": {
        "name": "←",
        "width": 1,
        "column": 13,
        "row": 4
    },
    "ArrowDown": {
        "name": "↓",
        "width": 1,
        "column": 14,
        "row": 4
    },
    "ArrowRight": {
        "name": "→",
        "width": 1,
        "column": 15,
        "row": 4
    }
}
